async_lightstreamer/__init__.py
async_lightstreamer/client.py
async_lightstreamer/exceptions.py
async_lightstreamer/subscription.py
async_lightstreamer-0.1.7.dist-info/METADATA
async_lightstreamer-0.1.7.dist-info/WHEEL
async_lightstreamer-0.1.7.dist-info/RECORD
