Metadata-Version: 2.1
Name: async-lightstreamer
Version: 0.1.7
Summary: 
Author: Seyed Mahdi Sadegh Shobeiri
Author-email: smss.lite@gmail.com
Requires-Python: >=3.8,<4.0
Classifier: Programming Language :: Python :: 3
Classifier: Programming Language :: Python :: 3.8
Classifier: Programming Language :: Python :: 3.9
Classifier: Programming Language :: Python :: 3.10
Classifier: Programming Language :: Python :: 3.11
Classifier: Programming Language :: Python :: 3.12
Requires-Dist: aiohttp (>=3.10.6,<4.0.0)
